supply_depot/__init__.py
supply_depot/trainer.py
supply_depot/cluster/__init__.py
supply_depot/cluster/cluster.py
supply_depot/cluster/ray_cluster.py
supply_depot/examples/__init__.py
supply_depot/examples/reinforce/__init__.py
supply_depot/examples/reinforce/mlp_agent.py
supply_depot/examples/reinforce/reinforce_trainer.py
supply_depot/rl/__init__.py
supply_depot/rl/agent/__init__.py
supply_depot/rl/agent/agent.py
supply_depot/rl/agent/gym_agent.py
supply_depot/rl/replay/__init__.py
supply_depot/rl/replay/base_replay_buffer.py
supply_depot/rl/replay/replay_buffer.py
supply_depot/rl/rollout/__init__.py
supply_depot/rl/rollout/gym_rollout.py
supply_depot/utils/__init__.py
supply_depot/utils/dict_utils.py
supply_depot/utils/torch_utils.py
supply_depot/utils/utils.py
supply_depot-0.1.0.dist-info/LICENSE
supply_depot-0.1.0.dist-info/METADATA
supply_depot-0.1.0.dist-info/WHEEL
supply_depot-0.1.0.dist-info/top_level.txt
supply_depot-0.1.0.dist-info/RECORD
